[
	{
		"id" : 1,
		"name" : "Audi"
	},
	{
		"id" : 2,
		"name" : "BMW"
	},
	{
		"id" : 3,
		"name" : "Chevrolet"
	},
	{
		"id" : 4,
		"name" : "Ford"
	},
	{
		"id" : 5,
		"name" : "Kia"
	},
	{
		"id" : 6,
		"name" : "Mazda"
	},
	{
		"id" : 7,
		"name" : "Mercedes"
	},
	{
		"id" : 8,
		"name" : "Mitsubishi"
	},
	{
		"id" : 9,
		"name" : "Toyota"
	},
	{
		"id" : 10,
		"name" : "Honda"
	},
	{
		"id" : 11,
		"name" : "Hyundai"
	},
	{
		"id" : 12,
		"name" : "Bentley"
	},
	{
		"id" : 13,
		"name" : "Lexus"
	},
	{
		"id" : 14,
		"name" : "Nissan"
	},
	{
		"id" : 15,
		"name" : "Porsche"
	},
	{
		"id" : 16,
		"name" : "Renault"
	},
	{
		"id" : 17,
		"name" : "Daewoo"
	},
	{
		"id" : 18,
		"name" : "Volkswagen"
	},
	{
		"id" : 19,
		"name" : "Suzuki"
	},
	{
		"id" : 20,
		"name" : "Luxgen"
	},
	{
		"id" : 21,
		"name" : "Cadillac"
	},
	{
		"id" : 22,
		"name" : "UAZ"
	},
	{
		"id" : 23,
		"name" : "Zoyte"
	},
	{
		"id" : 24,
		"name" : "Isuzu"
	},
	{
		"id" : 25,
		"name" : "Peugeot"
	},
	{
		"id" : 26,
		"name" : "SsangYong"
	},
	{
		"id" : 27,
		"name" : "Baic"
	}
]

